odoo/addons/printing_auto_label_printer/README.rst
odoo/addons/printing_auto_label_printer/__init__.py
odoo/addons/printing_auto_label_printer/__manifest__.py
odoo/addons/printing_auto_label_printer/i18n/it.po
odoo/addons/printing_auto_label_printer/i18n/printing_auto_label_printer.pot
odoo/addons/printing_auto_label_printer/models/__init__.py
odoo/addons/printing_auto_label_printer/models/printing_auto.py
odoo/addons/printing_auto_label_printer/readme/CONTRIBUTORS.rst
odoo/addons/printing_auto_label_printer/readme/DESCRIPTION.rst
odoo/addons/printing_auto_label_printer/static/description/icon.png
odoo/addons/printing_auto_label_printer/static/description/index.html
odoo/addons/printing_auto_label_printer/tests/__init__.py
odoo/addons/printing_auto_label_printer/tests/test_printing_auto_label_printer.py
odoo/addons/printing_auto_label_printer/views/printing_auto.xml
odoo14_addon_printing_auto_label_printer-14.0.1.0.1.dev5.dist-info/METADATA
odoo14_addon_printing_auto_label_printer-14.0.1.0.1.dev5.dist-info/WHEEL
odoo14_addon_printing_auto_label_printer-14.0.1.0.1.dev5.dist-info/top_level.txt
odoo14_addon_printing_auto_label_printer-14.0.1.0.1.dev5.dist-info/RECORD
